{
  "project_info": {
    "project_number": "747346931783",
    "project_id": "onemorepage-95e98",
    "storage_bucket": "onemorepage-95e98.appspot.com"
  },
  "client": [
    {
      "client_info": {
        "mobilesdk_app_id": "1:747346931783:android:6dfb5a5804cba6bd0dc162",
        "android_client_info": {
          "package_name": "com.example.a1morepage"
        }
      },
      "oauth_client": [
        {
          "client_id": "747346931783-vnvhjs0g87o55k0adumthje3qvafhd5t.apps.googleusercontent.com",
          "client_type": 3
        }
      ],
      "api_key": [
        {
          "current_key": "AIzaSyBbhsjuiaVYf3OUa7xFBgtP62-3HnhD2w0"
        }
      ],
      "services": {
        "appinvite_service": {
          "other_platform_oauth_client": [
            {
              "client_id": "747346931783-vnvhjs0g87o55k0adumthje3qvafhd5t.apps.googleusercontent.com",
              "client_type": 3
            }
          ]
        }
      }
    }
  ],
  "configuration_version": "1"
}